odoo10_addon_sale_owner_stock_sourcing-10.0.1.0.1-py3.8-nspkg.pth
odoo/addons/sale_owner_stock_sourcing/README.rst
odoo/addons/sale_owner_stock_sourcing/__init__.py
odoo/addons/sale_owner_stock_sourcing/__manifest__.py
odoo/addons/sale_owner_stock_sourcing/i18n/ca.po
odoo/addons/sale_owner_stock_sourcing/i18n/de.po
odoo/addons/sale_owner_stock_sourcing/i18n/es.po
odoo/addons/sale_owner_stock_sourcing/i18n/es_MX.po
odoo/addons/sale_owner_stock_sourcing/i18n/es_VE.po
odoo/addons/sale_owner_stock_sourcing/i18n/fr.po
odoo/addons/sale_owner_stock_sourcing/i18n/hr.po
odoo/addons/sale_owner_stock_sourcing/i18n/it.po
odoo/addons/sale_owner_stock_sourcing/i18n/nl_NL.po
odoo/addons/sale_owner_stock_sourcing/i18n/pt_BR.po
odoo/addons/sale_owner_stock_sourcing/i18n/pt_PT.po
odoo/addons/sale_owner_stock_sourcing/i18n/ro.po
odoo/addons/sale_owner_stock_sourcing/i18n/sale_owner_stock_sourcing.pot
odoo/addons/sale_owner_stock_sourcing/i18n/sl.po
odoo/addons/sale_owner_stock_sourcing/i18n/tr.po
odoo/addons/sale_owner_stock_sourcing/i18n/tr_TR.po
odoo/addons/sale_owner_stock_sourcing/i18n/vi_VN.po
odoo/addons/sale_owner_stock_sourcing/i18n/zh_CN.po
odoo/addons/sale_owner_stock_sourcing/model/__init__.py
odoo/addons/sale_owner_stock_sourcing/model/procurement.py
odoo/addons/sale_owner_stock_sourcing/model/sale_order.py
odoo/addons/sale_owner_stock_sourcing/security/group.xml
odoo/addons/sale_owner_stock_sourcing/static/description/icon.png
odoo/addons/sale_owner_stock_sourcing/tests/__init__.py
odoo/addons/sale_owner_stock_sourcing/tests/test_int_sale_to_reservation.py
odoo/addons/sale_owner_stock_sourcing/tests/test_propagate_owner_to_move.py
odoo/addons/sale_owner_stock_sourcing/view/sale_order.xml
odoo10_addon_sale_owner_stock_sourcing-10.0.1.0.1.dist-info/METADATA
odoo10_addon_sale_owner_stock_sourcing-10.0.1.0.1.dist-info/WHEEL
odoo10_addon_sale_owner_stock_sourcing-10.0.1.0.1.dist-info/namespace_packages.txt
odoo10_addon_sale_owner_stock_sourcing-10.0.1.0.1.dist-info/top_level.txt
odoo10_addon_sale_owner_stock_sourcing-10.0.1.0.1.dist-info/RECORD
